cvindrones/__init__.py
cvindrones/main.py
cvindrones-0.0.2.dist-info/METADATA
cvindrones-0.0.2.dist-info/WHEEL
cvindrones-0.0.2.dist-info/top_level.txt
cvindrones-0.0.2.dist-info/RECORD
