Metadata-Version: 2.1
Name: cvindrones
Version: 0.0.2
Summary: Direct Implementation of computer vision with just a line of code
Home-page: https://www.lakshaykumar.tech/
Author: Lakshay Kumar
Author-email: contact@lakshaykumar.tech
License: UNKNOWN
Download-URL: https://github.com/laksh-2193/coterie/archive/refs/tags/v0.0.1.tar.gz
Platform: UNKNOWN
Classifier: Programming Language :: Python :: 3
Classifier: License :: OSI Approved :: MIT License
Classifier: Operating System :: OS Independent
Requires-Python: >=3.3
Requires-Dist: mediapipe
